LICENSE.md
README.md
pyproject.toml
src/saxsmart/__init__.py
src/saxsmart/app.py
src/saxsmart/callbacks.py
src/saxsmart/layout.py
src/saxsmart/utils.py
src/saxsmart.egg-info/PKG-INFO
src/saxsmart.egg-info/SOURCES.txt
src/saxsmart.egg-info/dependency_links.txt
src/saxsmart.egg-info/entry_points.txt
src/saxsmart.egg-info/requires.txt
src/saxsmart.egg-info/top_level.txt
src/saxsmart/assets/bm29_logo.png
src/saxsmart/assets/custom.css
src/saxsmart/assets/esrf_logo.png
src/saxsmart/example_data/SASDUE4.dat
src/saxsmart/example_data/sasdue4.fasta
src/saxsmart/example_data/sasdue4.pdb
src/saxsmart/tests/test_dummy.py