Metadata-Version: 2.4
Name: saxsmart
Version: 1.0.0
Summary: SAXSMART: SAXS modeling and refinement toolkit (Dash app)
Author: Hayden Fisher
License: MIT
Project-URL: Homepage, https://gitlab.esrf.fr/hayden5a/saxsmart
Keywords: SAXS,PEPSI-SAXS,Dash,bioinformatics,scattering
Requires-Python: >=3.9
License-File: LICENSE.md
Requires-Dist: dash<=2.18.0
Requires-Dist: dash[diskcache]<=2.18.0
Requires-Dist: dash_bootstrap_components<=1.7.1
Requires-Dist: diskcache
Requires-Dist: plotly>=5.20
Requires-Dist: pandas>=2.2
Requires-Dist: numpy>=1.26
Requires-Dist: biopython>=1.84
Requires-Dist: requests>=2.32
Requires-Dist: dash-molstar>=0.5.0
Requires-Dist: scipy>=1.13
Dynamic: license-file
